tcp/__init__.py
tcp/aio.py
tcp/channel.py
tcp/hub.py
tcp/startrek.py
tcp-2.2.2.dist-info/METADATA
tcp-2.2.2.dist-info/WHEEL
tcp-2.2.2.dist-info/top_level.txt
tcp-2.2.2.dist-info/RECORD
