Metadata-Version: 2.1
Name: tcp
Version: 2.2.2
Summary: Transmission Control Protocol
Home-page: https://github.com/moky/wormhole/
Author: Albert Moky
Author-email: albert.moky@gmail.com
License: MIT
Platform: UNKNOWN
Classifier: Programming Language :: Python :: 3
Classifier: License :: OSI Approved :: MIT License
Classifier: Operating System :: OS Independent
